[
    {"ilce_ID": "1", "sehir_ID":"1","ilce_adi":"Yüreğir"},
    {"ilce_ID": "2", "sehir_ID":"1","ilce_adi":"Seyhan"},
    {"ilce_ID": "3", "sehir_ID":"1","ilce_adi":"Ceyhan"},
    {"ilce_ID": "4", "sehir_ID":"1","ilce_adi":"Çukurova"},
    {"ilce_ID": "5", "sehir_ID":"1","ilce_adi":"Sarıçam"},
    {"ilce_ID": "6", "sehir_ID":"1","ilce_adi":"Kozan"},
    {"ilce_ID": "7", "sehir_ID":"1","ilce_adi":"Feke"},
    {"ilce_ID": "8", "sehir_ID":"2","ilce_adi":"Besni"},
    {"ilce_ID": "9", "sehir_ID":"2","ilce_adi":"Çelikhan"},
    {"ilce_ID": "10", "sehir_ID":"2","ilce_adi":"Gerger"},
    {"ilce_ID": "11", "sehir_ID":"2","ilce_adi":"Gölbaşı"},
    {"ilce_ID": "12", "sehir_ID":"2","ilce_adi":"Kâhta"},
    {"ilce_ID": "13", "sehir_ID":"2","ilce_adi":"Samsat"},
    {"ilce_ID": "14", "sehir_ID":"2","ilce_adi":"Sincik"},
    {"ilce_ID": "15", "sehir_ID":"3","ilce_adi":"Başmakçı"},
    {"ilce_ID": "16", "sehir_ID":"3","ilce_adi":"Bayat"},
    {"ilce_ID": "17", "sehir_ID":"3","ilce_adi":"Bolvadin"},
    {"ilce_ID": "18", "sehir_ID":"3","ilce_adi":"Çay"},
    {"ilce_ID": "19", "sehir_ID":"3","ilce_adi":"Çobanlar"},
    {"ilce_ID": "20", "sehir_ID":"3","ilce_adi":"Dazkırı"},
    {"ilce_ID": "21", "sehir_ID":"4","ilce_adi":"Diyadin"},
    {"ilce_ID": "22", "sehir_ID":"4","ilce_adi":"Doğubayazıt"},
    {"ilce_ID": "23", "sehir_ID":"4","ilce_adi":"Eleşkirt"},
    {"ilce_ID": "24", "sehir_ID":"4","ilce_adi":"Hamur"},
    {"ilce_ID": "25", "sehir_ID":"4","ilce_adi":"Patnos"},
    {"ilce_ID": "26", "sehir_ID":"4","ilce_adi":"Taşlıçay"},
    {"ilce_ID": "27", "sehir_ID":"4","ilce_adi":"Tutak"}
]